tpypi/__init__.py
tpypi/oh.py
ttpypi-0.0.2.dist-info/LICENSE
ttpypi-0.0.2.dist-info/METADATA
ttpypi-0.0.2.dist-info/WHEEL
ttpypi-0.0.2.dist-info/top_level.txt
ttpypi-0.0.2.dist-info/RECORD
