Metadata-Version: 2.1
Name: ttpypi
Version: 0.0.2
Summary: 测试包
Home-page: https://www.baidu.com
Author: A Big Boby
Author-email: ilikepython@163.com
License: UNKNOWN
Platform: UNKNOWN
Classifier: Programming Language :: Python :: 3
Classifier: License :: OSI Approved :: MIT License
Classifier: Operating System :: OS Independent
License-File: LICENSE
